jivas/__init__.py
jivas/agent/__init__.py
jivas/agent/lib.jac
jivas/agent/action/__init__.py
jivas/agent/action/action.jac
jivas/agent/action/action_webhook_walker.jac
jivas/agent/action/actions.jac
jivas/agent/action/agent_graph_walker.jac
jivas/agent/action/do_pulse.jac
jivas/agent/action/exit_interact_action.jac
jivas/agent/action/get_action.jac
jivas/agent/action/get_action_app.jac
jivas/agent/action/install_action.jac
jivas/agent/action/interact.jac
jivas/agent/action/interact_action.jac
jivas/agent/action/interview_interact_action.jac
jivas/agent/action/list_actions.jac
jivas/agent/action/model_action.jac
jivas/agent/action/retrieval_action.jac
jivas/agent/action/retrieval_interact_action.jac
jivas/agent/action/stt.jac
jivas/agent/action/stt_action.jac
jivas/agent/action/tts_action.jac
jivas/agent/action/uninstall_action.jac
jivas/agent/action/update_action.jac
jivas/agent/action/vector_store_action.jac
jivas/agent/action/subgraph_action/completed_state.jac
jivas/agent/action/subgraph_action/confirmed_state.jac
jivas/agent/action/subgraph_action/initial_state.jac
jivas/agent/action/subgraph_action/list_states.jac
jivas/agent/action/subgraph_action/revision_state.jac
jivas/agent/action/subgraph_action/state.jac
jivas/agent/action/subgraph_action/subgraph_action.jac
jivas/agent/action/subgraph_action/update_state.jac
jivas/agent/analytics/__init__.py
jivas/agent/analytics/get_channels_by_date.jac
jivas/agent/analytics/get_interaction_logs.jac
jivas/agent/analytics/get_interactions_by_date.jac
jivas/agent/analytics/get_users_by_date.jac
jivas/agent/core/__init__.py
jivas/agent/core/agent.jac
jivas/agent/core/agents.jac
jivas/agent/core/app.jac
jivas/agent/core/delete_agent.jac
jivas/agent/core/exec_reload.jac
jivas/agent/core/export_daf.jac
jivas/agent/core/export_descriptor.jac
jivas/agent/core/get_agent.jac
jivas/agent/core/graph_node.jac
jivas/agent/core/graph_object.jac
jivas/agent/core/graph_walker.jac
jivas/agent/core/healthcheck.jac
jivas-2.1.25.dist-info/METADATA
jivas-2.1.25.dist-info/WHEEL
jivas-2.1.25.dist-info/top_level.txt
jivas-2.1.25.dist-info/RECORD
