Metadata-Version: 2.4
Name: jivas
Version: 2.1.25
Summary: JIVAS is an Agentic Framework for rapidly prototyping and deploying graph-based, AI solutions.
Home-page: https://github.com/TrueSelph/jivas
Author: TrueSelph Inc.
Author-email: admin@trueselph.com
Keywords: jivas
Requires-Python: >=3.12.0
Requires-Dist: jvcli
Requires-Dist: jvclient
Requires-Dist: jvserve
Requires-Dist: jac-cloud==0.2.7
Requires-Dist: jaclang==0.8.7
Requires-Dist: pytz==2025.2
Requires-Dist: types-pytz==2025.2.0.20250809
Requires-Dist: schedule==1.2.2
Requires-Dist: openai==1.109.1
Requires-Dist: langchain==0.3.27
Requires-Dist: langchain-community==0.3.27
Requires-Dist: langchain-core==0.3.79
Requires-Dist: langchain-experimental==0.3.4
Requires-Dist: langchain-openai==0.3.19
Requires-Dist: langchain-text-splitters==0.3.11
Requires-Dist: langsmith==0.4.38
Requires-Dist: setuptools==80.9.0
Requires-Dist: transformers==4.57.1
Requires-Dist: ftfy==6.3.1
Provides-Extra: dev
Requires-Dist: pre-commit; extra == "dev"
Requires-Dist: pytest; extra == "dev"
Requires-Dist: pytest-mock; extra == "dev"
Requires-Dist: pytest-cov; extra == "dev"
Requires-Dist: coverage; extra == "dev"
Dynamic: author
Dynamic: author-email
Dynamic: description
Dynamic: description-content-type
Dynamic: home-page
Dynamic: keywords
Dynamic: provides-extra
Dynamic: requires-dist
Dynamic: requires-python
Dynamic: summary
